{
  "db_name": "PostgreSQL",
  "query": "SELECT i.id AS \"id: LiquidationObligationId\", e.sequence, e.event, e.recorded_at FROM core_liquidation_obligations i JOIN core_liquidation_obligation_events e ON i.id = e.id WHERE i.id = ANY($1) ORDER BY i.id, e.sequence",
  "describe": {
    "columns": [
      {
        "ordinal": 0,
        "name": "id: LiquidationObligationId",
        "type_info": "Uuid"
      },
      {
        "ordinal": 1,
        "name": "sequence",
        "type_info": "Int4"
      },
      {
        "ordinal": 2,
        "name": "event",
        "type_info": "Jsonb"
      },
      {
        "ordinal": 3,
        "name": "recorded_at",
        "type_info": "Timestamptz"
      }
    ],
    "parameters": {
      "Left": [
        "UuidArray"
      ]
    },
    "nullable": [
      false,
      false,
      false,
      false
    ]
  },
  "hash": "55f5a8293b8e431bea4755e5dc589c79ea62f7bf976fb7705020e2762b6002af"
}
